ant_nest/__init__.py
ant_nest/_settings_example.py
ant_nest/ant.py
ant_nest/cli.py
ant_nest/exceptions.py
ant_nest/items.py
ant_nest/pipelines.py
ant_nest/pool.py
ant_nest/reporter.py
ant_nest/utils.py
ant_nest-1.0.1.dist-info/entry_points.txt
ant_nest-1.0.1.dist-info/LICENSE
ant_nest-1.0.1.dist-info/WHEEL
ant_nest-1.0.1.dist-info/METADATA
ant_nest-1.0.1.dist-info/RECORD
