Metadata-Version: 2.1
Name: ant-nest
Version: 1.0.1
Summary: A simple and clear Web Crawler framework build on python3.6+
Home-page: https://github.com/strongbugman/ant_nest
License: LGPL
Author: strongbugman
Author-email: strongbugman@gmail.com
Requires-Python: >=3.6,<4.0
Classifier: Environment :: Console
Classifier: License :: Other/Proprietary License
Classifier: Programming Language :: Python :: 3
Classifier: Programming Language :: Python :: 3.6
Classifier: Programming Language :: Python :: 3.7
Classifier: Programming Language :: Python :: 3.8
Classifier: Programming Language :: Python :: 3.9
Classifier: Topic :: Internet :: WWW/HTTP
Classifier: Topic :: Software Development :: Libraries :: Application Frameworks
Classifier: Topic :: Software Development :: Libraries :: Python Modules
Requires-Dist: IPython (>=7.0)
Requires-Dist: aiofiles (>=0.3.1)
Requires-Dist: httpx (>=0.14.0)
Requires-Dist: tenacity (>=4.8.0)
Requires-Dist: typing_extensions (>=3.6)
Requires-Dist: ujson (>=1.3.4)
Project-URL: Repository, https://github.com/strongbugman/ant_nest
